[
    {
        "id": 1,
        "Icon": "https://github.com/Dev-Rook/minimal-portfolio/blob/main/src/Assets/Icons/React-Icon.png?raw=true",
        "Title": "React JS",
        "Description": "React is a free and open-source front-end JavaScript library for building user interfaces based on components"
    },
    {
        "id": 2,
        "Icon": "https://github.com/Dev-Rook/rook/blob/main/src/assets/icons/astrojs-icon.jpeg?raw=true",
        "Title": "Astro JS",
        "Description": "React is a free and open-source front-end JavaScript library for building user interfaces based on components"
    },
    {
        "id": 3,
        "Icon": "https://github.com/Dev-Rook/rook/blob/main/src/assets/icons/express-icon.png?raw=true",
        "Title": "Express",
        "Description": "React is a free and open-source front-end JavaScript library for building user interfaces based on components"
    },
    {
        "id": 4,
        "Icon": "https://github.com/Dev-Rook/rook/blob/main/src/assets/icons/node-js.png?raw=true",
        "Title": "Node JS",
        "Description": "React is a free and open-source front-end JavaScript library for building user interfaces based on components"
    },
    {
        "id": 5,
        "Icon": "https://github.com/Dev-Rook/rook/blob/main/src/assets/icons/redux.png?raw=true",
        "Title": "Redux-Toolkit",
        "Description": "React is a free and open-source front-end JavaScript library for building user interfaces based on components"
    },
    {
        "id": 6,
        "Icon": "https://github.com/Dev-Rook/rook/blob/main/src/assets/icons/mongodb-icon.png?raw=true",
        "Title": "Mongodb",
        "Description": "React is a free and open-source front-end JavaScript library for building user interfaces based on components"
    },
    {
        "id": 7,
        "Icon": "https://github.com/Dev-Rook/rook/blob/main/src/assets/icons/postman-icon.png?raw=true",
        "Title": "Postman",
        "Description": "React is a free and open-source front-end JavaScript library for building user interfaces based on components"
    },
    {
        "id": 8,
        "Icon": "https://github.com/Dev-Rook/minimal-portfolio/blob/main/src/Assets/Icons/MaterialUI-Logo.png?raw=true",
        "Title": "Material Ui",
        "Description": "React is a free and open-source front-end JavaScript library for building user interfaces based on components"
    },
    {
        "id": 9,
        "Icon": "https://raw.githubusercontent.com/Dev-Rook/minimal-portfolio/2f1fe21347b5d7ed595b9333ff025318e03ad9ba/src/Assets/Icons/Npm-Logo.svg",
        "Title": "NPM",
        "Description": "React is a free and open-source front-end JavaScript library for building user interfaces based on components"
    }
]